{"GlobalPropertiesHash":"bYzSbA4IgTYL0MvGmKCAqeRSpMEFOtMGe9gBbt6b5V0=","FingerprintPatternsHash":"gq3WsqcKBUGTSNle7RKKyXRIwh7M8ccEqOqYvIzoM04=","PropertyOverridesHash":"8ZRc1sGeVrPBx4lD717BgRaQekyh78QKV9SKsdt638U=","InputHashes":["jjWgH1BNTh1POazAtEFf/0HQ7H2sTVQelEM4kP1TauU=","W74RQzvA7c7TdO95h\u002BkIU\u002BXqdxbIk/QCHcEAGyixfM4=","ZbTNod\u002BZIvfyYbNVA/na9cgbB7oUCCb95Cq77YrRW4M=","b2aqDYzWIW7A/19P4nkBb8QktRSFfZ/DjNzgiWh0QY8=","3Opf\u002BI1kUZM9aH5hujkSrx/ZNTzRSWG0Jqzi5j0Krwc=","z5T7JBAaXjbCgVI\u002B6ItK56WT\u002BEWCCDRcEhKsqyvTijg=","l3uHfNbBhTCR6xwYn4EbBvHMUiwD9x3zfCr46lGpAOo=","nNf7SowWTE597bLrDdneLXDkSCTzjkjlSyMZZXLgpCE=","CkIB/uQ\u002BnYlaYynH\u002BN4VvTMpwbefRY5zRFnilD2yWrA=","indVqD7Il1KebHFyhEllcSbf7MIw/Np/A3K4Lww98tM=","7Yf3Q15ftTE\u002B3d5VHNNncFYApl8cL9a7LvQT4TQDxzc=","jdsWAqEsLYU48epT2h32W1wxjjCFwAU7K\u002BZekv48uGk=","BWRM1b3AHqaxTH4FPKlZMcEU/PV\u002B01qq96tUGLAj\u002Bf8="],"CachedAssets":{"jjWgH1BNTh1POazAtEFf/0HQ7H2sTVQelEM4kP1TauU=":{"Identity":"D:\\Darbar\\Applications\\Darul Irfan Research Institute\\DiriWebPortal\\DiriWebAdmin\\wwwroot\\css\\site.css","SourceId":"DiriWebAdmin","SourceType":"Discovered","ContentRoot":"D:\\Darbar\\Applications\\Darul Irfan Research Institute\\DiriWebPortal\\DiriWebAdmin\\wwwroot\\","BasePath":"/","RelativePath":"css/site#[.{fingerprint}]?.css","AssetKind":"All","AssetMode":"All","AssetRole":"Primary","AssetMergeBehavior":null,"AssetMergeSource":"","RelatedAsset":null,"AssetTraitName":null,"AssetTraitValue":null,"Fingerprint":"oq8r4nbcb2","Integrity":"AKvNjO3dCPPS0eSU1Ez8T2wI280i08yGycV9ndytL\u002Bc=","CopyToOutputDirectory":"Never","CopyToPublishDirectory":"PreserveNewest","OriginalItemSpec":"wwwroot\\css\\site.css","FileLength":194,"LastWriteTime":"2026-01-21T07:45:09.5761286+00:00"},"W74RQzvA7c7TdO95h\u002BkIU\u002BXqdxbIk/QCHcEAGyixfM4=":{"Identity":"D:\\Darbar\\Applications\\Darul Irfan Research Institute\\DiriWebPortal\\DiriWebAdmin\\wwwroot\\favicon.ico","SourceId":"DiriWebAdmin","SourceType":"Discovered","ContentRoot":"D:\\Darbar\\Applications\\Darul Irfan Research Institute\\DiriWebPortal\\DiriWebAdmin\\wwwroot\\","BasePath":"/","RelativePath":"favicon#[.{fingerprint}]?.ico","AssetKind":"All","AssetMode":"All","AssetRole":"Primary","AssetMergeBehavior":null,"AssetMergeSource":"","RelatedAsset":null,"AssetTraitName":null,"AssetTraitValue":null,"Fingerprint":"61n19gt1b8","Integrity":"Jtxf9L\u002B5ITKRc1gIRl4VbUpGkRNfOBXjYTdhJD4facM=","CopyToOutputDirectory":"Never","CopyToPublishDirectory":"PreserveNewest","OriginalItemSpec":"wwwroot\\favicon.ico","FileLength":5430,"LastWriteTime":"2026-01-21T07:45:09.5761286+00:00"},"ZbTNod\u002BZIvfyYbNVA/na9cgbB7oUCCb95Cq77YrRW4M=":{"Identity":"D:\\Darbar\\Applications\\Darul Irfan Research Institute\\DiriWebPortal\\DiriWebAdmin\\wwwroot\\js\\site.js","SourceId":"DiriWebAdmin","SourceType":"Discovered","ContentRoot":"D:\\Darbar\\Applications\\Darul Irfan Research Institute\\DiriWebPortal\\DiriWebAdmin\\wwwroot\\","BasePath":"/","RelativePath":"js/site#[.{fingerprint}]?.js","AssetKind":"All","AssetMode":"All","AssetRole":"Primary","AssetMergeBehavior":null,"AssetMergeSource":"","RelatedAsset":null,"AssetTraitName":null,"AssetTraitValue":null,"Fingerprint":"6b9nfc4n3r","Integrity":"4q1jwFhaPaZgr8WAUSrux6hAuh0XDg9kPS3xIVq36I0=","CopyToOutputDirectory":"Never","CopyToPublishDirectory":"PreserveNewest","OriginalItemSpec":"wwwroot\\js\\site.js","FileLength":230,"LastWriteTime":"2026-01-21T07:45:09.5917579+00:00"}},"CachedCopyCandidates":{}}